bolsasfnde/__init__.py
bolsasfnde/__main__.py
bolsasfnde/main.py
bolsasfnde-3.4.dist-info/LICENSE
bolsasfnde-3.4.dist-info/METADATA
bolsasfnde-3.4.dist-info/WHEEL
bolsasfnde-3.4.dist-info/entry_points.txt
bolsasfnde-3.4.dist-info/top_level.txt
bolsasfnde-3.4.dist-info/RECORD
