Metadata-Version: 2.1
Name: bolsasfnde
Version: 3.4
Summary: A biblioteca automatiza consultas periódicas ao site do FNDE para verificar se a tão esperada bolsa foi concedida. Adeus às verificações manuais repetitivas!
Requires-Python: >=3.6
License-File: LICENSE
Requires-Dist: requests
